tests/__init__.py
tests/test_flags.py
tests/test_thaw.py
thaw/__init__.py
thaw/__main__.py
thaw/thaw.py
thaw-1.0.1.dist-info/LICENSE.txt
thaw-1.0.1.dist-info/METADATA
thaw-1.0.1.dist-info/WHEEL
thaw-1.0.1.dist-info/entry_points.txt
thaw-1.0.1.dist-info/top_level.txt
thaw-1.0.1.dist-info/RECORD
