Metadata-Version: 2.1
Name: thaw
Version: 1.0.1
Summary: Generates report showing where dependencies affect your project
Home-page: https://github.com/kateapault/pip-thaw
Author: Kate Raskauskas
Author-email: kateapault@gmail.com
License: UNKNOWN
Download-URL: https://github.com/kateapault/pip-thaw/archive/v1.0.1.tar.gz
Keywords: thaw update freeze pip requirements library manage package development project
Platform: UNKNOWN
Classifier: Programming Language :: Python :: 3
Classifier: Topic :: Software Development
Classifier: License :: OSI Approved :: MIT License
Classifier: Operating System :: MacOS
Requires-Python: >=3.0
